{
"type": "FeatureCollection",
"name": "CENTRO DE TECNOLOGIAS",
"crs": { "type": "name", "properties": { "name": "urn:ogc:def:crs:OGC:1.3:CRS84" } },
"features": [
{ "type": "Feature", "properties": { "id": 1 }, "geometry": { "type": "Point", "coordinates": [ -48.944141224111121, -16.292465207110499 ] } }
]
}
